fact_checker/__init__.py
fact_checker/main.py
fact_checker-0.1.0.dist-info/METADATA
fact_checker-0.1.0.dist-info/WHEEL
fact_checker-0.1.0.dist-info/top_level.txt
fact_checker-0.1.0.dist-info/RECORD
